{
  "fr": {
    "nav": {
      "home": "Accueil",
      "about": "À propos",
      "skills": "Compétences",
      "experiences": "Expériences",
      "projects": "Projets",
      "articles": "Articles",
      "cv": "CV",
      "contact": "Contact"
    },
    "hero": {
      "subtitle": "UI/UX Developer | Junior Web3 Developer – Cardano Blockchain | Formateur Web3 & Contributeur Communautaire | Rédacteur Technique | Créateur de Contenus Web3 | Reviseur – Project Catalyst Cardano",
      "bio": "Spécialisé dans l'écosystème Cardano, la formation et la création de contenus Web3.",
      "downloadCv": "Télécharger le CV"
    },
    "about": {
      "title": "À propos de moi",
      "text1": "Je suis UI/UX Developer et Junior Web3 Developer, spécialisé dans la blockchain Cardano. Mon travail combine les technologies web modernes avec l'innovation blockchain pour créer des expériences numériques intuitives et centrées utilisateur.",
      "text2": "Au-delà du développement, je contribue activement à la croissance de l'écosystème Cardano et Web3 en RD Congo grâce à la formation, à l'engagement communautaire et à la rédaction technique. J'accompagne l'onboarding des nouveaux membres, crée des contenus éducatifs et aide à faire le lien entre Web2 et Web3.",
      "text3": "Passionné par la blockchain et l'apprentissage continu, je vise à développer des solutions impactantes tout en renforçant les communautés par la technologie et le partage de connaissances."
    },
    "skills": {
      "title": "Compétences",
      "frontend": "Frontend",
      "backend": "Backend",
      "blockchain": "Blockchain & Cardano",
      "tools": "Outils",
      "certifications": "Certifications",
      "certified": "Certifié"
    },
    "experiences": {
      "title": "Expériences",
      "loading": "Chargement des expériences...",
      "noExperiences": "Aucune expérience renseignée pour le moment.",
      "loadMore": "Voir plus",
      "loadLess": "Voir moins"
    },
    "projects": {
      "title": "Mes Projets",
      "loading": "Chargement des projets...",
      "noProjects": "Aucun projet disponible pour le moment.",
      "viewCode": "Code",
      "viewDemo": "Démo",
      "loadMore": "Charger plus",
      "loadLess": "Charger moins"
    },
    "articles": {
      "title": "Articles & Publications",
      "loading": "Chargement des articles...",
      "noArticles": "Aucun article disponible pour le moment.",
      "readArticle": "Lire l'article",
      "loadMore": "Voir plus",
      "loadLess": "Voir moins"
    },
    "cv": {
      "title": "Mon CV",
      "view": "Voir le CV",
      "hide": "Masquer le CV",
      "download": "Télécharger le CV (PDF)"
    },
    "contact": {
      "title": "Contactez-moi",
      "social": "Réseaux sociaux",
      "form": "Formulaire de contact",
      "name": "Nom",
      "email": "Email",
      "subject": "Sujet",
      "message": "Message",
      "send": "Envoyer",
      "sent": "Message envoyé !"
    },
    "footer": {
      "rights": "Tous droits réservés.",
      "developed": "Développé avec",
      "and": "et passion"
    }
  },
  "en": {
    "nav": {
      "home": "Home",
      "about": "About",
      "skills": "Skills",
      "experiences": "Experience",
      "projects": "Projects",
      "articles": "Articles",
      "cv": "Resume",
      "contact": "Contact"
    },
    "hero": {
      "subtitle": "UI/UX Developer | Junior Web3 Developer – Cardano Blockchain | Web3 Trainer & Community Contributor | Technical Writer | Web3 Content Creator | Reviewer – Project Catalyst Cardano",
      "bio": "Specialized in the Cardano ecosystem, training and Web3 content creation.",
      "downloadCv": "Download Resume"
    },
    "about": {
      "title": "About Me",
      "text1": "I am a UI/UX Developer and Junior Web3 Developer, specialized in the Cardano blockchain. My work combines modern web technologies with blockchain innovation to create intuitive, user-centered digital experiences.",
      "text2": "Beyond development, I actively contribute to the growth of the Cardano and Web3 ecosystem in DR Congo through training, community engagement and technical writing. I support onboarding of new members, create educational content and help bridge Web2 and Web3.",
      "text3": "Passionate about blockchain and continuous learning, I aim to develop impactful solutions while strengthening communities through technology and knowledge sharing."
    },
    "skills": {
      "title": "Skills",
      "frontend": "Frontend",
      "backend": "Backend",
      "blockchain": "Blockchain & Cardano",
      "tools": "Tools",
      "certifications": "Certifications",
      "certified": "Certified"
    },
    "experiences": {
      "title": "Experience",
      "loading": "Loading experience...",
      "noExperiences": "No experience listed yet.",
      "loadMore": "Load more",
      "loadLess": "Load less"
    },
    "projects": {
      "title": "My Projects",
      "loading": "Loading projects...",
      "noProjects": "No projects available at the moment.",
      "viewCode": "Code",
      "viewDemo": "Demo",
      "loadMore": "Load more",
      "loadLess": "Load less"
    },
    "articles": {
      "title": "Articles & Publications",
      "loading": "Loading articles...",
      "noArticles": "No articles available at the moment.",
      "readArticle": "Read article",
      "loadMore": "Load more",
      "loadLess": "Load less"
    },
    "cv": {
      "title": "My Resume",
      "view": "View resume",
      "hide": "Hide resume",
      "download": "Download Resume (PDF)"
    },
    "contact": {
      "title": "Contact Me",
      "social": "Social Networks",
      "form": "Contact Form",
      "name": "Name",
      "email": "Email",
      "subject": "Subject",
      "message": "Message",
      "send": "Send",
      "sent": "Message sent!"
    },
    "footer": {
      "rights": "All rights reserved.",
      "developed": "Developed with",
      "and": "and passion"
    }
  }
}

